phonon_finiteK/__init__.py
phonon_finiteK/bz.py
phonon_finiteK/cell.py
phonon_finiteK/dynam.py
phonon_finiteK/main.py
phonon_finiteK/params.py
phonon_finiteK/plot.py
phonon_finiteK-0.0.14.data/scripts/phonon-finiteK
phonon_finiteK-0.0.14.dist-info/LICENSE
phonon_finiteK-0.0.14.dist-info/METADATA
phonon_finiteK-0.0.14.dist-info/WHEEL
phonon_finiteK-0.0.14.dist-info/top_level.txt
phonon_finiteK-0.0.14.dist-info/RECORD
