Metadata-Version: 2.1
Name: phonon-finiteK
Version: 0.0.14
Summary: Finite K phonon package
Home-page: https://gitlab.com/Coiana/phonon_finiteK
Author: Gabriele Coiana
Author-email: gabriele.coiana17@imperial.ac.uk
License: UNKNOWN
Platform: UNKNOWN
Classifier: Programming Language :: Python :: 3
Classifier: License :: OSI Approved :: MIT License
Classifier: Operating System :: OS Independent
